<?xml version="1.0" encoding="UTF-8" ?>
<!DOCTYPE struts PUBLIC
	"-//Apache Software Foundation//DTD Struts Configuration 2.3//EN"
	"http://struts.apache.org/dtds/struts-2.3.dtd">


<struts>

	<!-- 开启开发模式，这样出错会有更详细的显示信息，便于调试 -->
	<constant name="struts.devMode" value="true" />
	<!-- 设置action请求的后缀名 -->
	<constant name="struts.action.extension" value="action,html,," />
	<!-- 是否开启 DMI 模式，默认不建议开启，会导致严重的安全问题 -->
	<constant name="struts.enable.DynamicMethodInvocation" value="false" />


 
	<!-- 第一个模块，登陆注册 -->
	<package name="login" namespace="/login" extends="struts-default">

		<global-results>
			<result name="error">/WEB-INF/jsp/login/error.jsp</result>
			<result name="Nopower">/WEB-INF/jsp/login/Nopower.jsp</result>
		</global-results>

		<global-exception-mappings>
			<exception-mapping result="error" exception="java.lang.Exception"></exception-mapping>
		</global-exception-mappings>
  
		<!-- 显示登录的主页面 -->
		<!-- 请求的 url 为 localhost:8088/hello/login/login.action -->
		<action name="login">
			<result>/WEB-INF/jsp/login/login.jsp</result>
		</action>

		<!-- 完成登录相关的操作 -->
		<!-- 请求的 url 为 localhost:8088/hello/login/loginSubmit.action -->
		<action name="loginSubmit" class="com.s126.demo.action.LoginAction"
			method="login">
			<!-- 类型，重定向和转发 -->
			<result name="success" type="redirect">/emp/listAll.html</result>
			<result name="fail">/WEB-INF/jsp/login/fail.jsp</result>
			<result name="error">/WEB-INF/jsp/login/fail.jsp</result>
			<result name="input">/WEB-INF/jsp/login/login.jsp</result>
		</action>

		<!-- 显示注册的页面 -->
		<!-- 请求的 url 为 localhost:8088/hello/login/register.action -->
		<action name="register" class="com.s126.demo.action.LoginAction" method="registerIndex">
			<result>/WEB-INF/jsp/login/register.jsp</result>
		</action>

		<!-- 完成注册相关的操作 -->
		<!-- 请求的 url 为 localhost:8088/hello/login/registerSubmit.action -->
		<action name="registerSubmit" class="com.s126.demo.action.LoginAction" method="register">
			<result name="success">/WEB-INF/jsp/login/welcome.jsp</result>
			<result name="fails">/WEB-INF/jsp/login/fail.jsp</result>
			<result name="input">/WEB-INF/jsp/login/register.jsp</result>
		</action>
		
	</package>




	<!-- 第二个模块，员工管理 -->
	<package name="emp" namespace="/emp" extends="login">
	
		<!-- 声明自定义拦截器 -->
		<interceptors>
			<interceptor name="isLogin" class="com.s126.demo.interceptor.ListAllInterceptor"></interceptor>
			<interceptor name="isDelete" class="com.s126.demo.interceptor.DeleteInterceptor"></interceptor>
		
		</interceptors>
		
		<action name="*" class="com.s126.demo.action.EmpAction" method="{1}">
			<result name="listAll">/WEB-INF/jsp/emp/listAll.jsp</result>
			<result name="ierror" type="redirect">/login/login.html</result>
			<result name="update">/WEB-INF/jsp/emp/update.jsp</result>
			<result name="add">/WEB-INF/jsp/emp/add.jsp</result>
			<result name="delete">/WEB-INF/jsp/emp/delete.jsp</result>
		</action>
	</package>




	<!-- 第三个模块，商品管理 -->
	<package name="product" namespace="/product">
		<!-- 大家自行实现 -->
	</package>
	
	
	
	
	
	<!-- 测试模块 -->
	<package name="test" namespace="/test" extends="struts-default">
		
		<!-- 这是一个拦截器的测试请求 -->
		<!-- 首先自定义两个拦截器 -->
		<!-- 请大家自己调试下代码，了解下拦截器的大致流程。 -->
		<interceptors>
			<interceptor name="aaa" class="com.s126.demo.test.interceptor.AI"></interceptor>
			<interceptor name="bbb" class="com.s126.demo.test.interceptor.BI"></interceptor>
		</interceptors>
		<action name="interceptor" class="com.s126.demo.test.TestAction" method="testInterceptor">
			<!-- 这个请求使用下面两个定义的拦截器。可以执行看看输出顺序 -->
			<interceptor-ref name="aaa" />
			<interceptor-ref name="bbb" />
			<result>/WEB-INF/jsp/login/error.jsp</result>
		</action>
		
		
		<action name="testNoDefault" class="com.s126.demo.test.TestAction" method="testNoDefault">
			<result>/WEB-INF/jsp/test/testNoDefault.jsp</result>
			<interceptor-ref name="aaa"></interceptor-ref>
			<interceptor-ref name="defaultStack"></interceptor-ref>
		</action>

		<!-- 这是一个测试 ognl的请求 -->
		<action name="ognl" class="com.s126.demo.test.OgnlAction" method="testOGNL">
			<result>/WEB-INF/jsp/test/ognl.jsp</result>
		</action>
	</package>


</struts>
